LICENSE
README.md
setup.py
lib/frontai.egg-info/PKG-INFO
lib/frontai.egg-info/SOURCES.txt
lib/frontai.egg-info/dependency_links.txt
lib/frontai.egg-info/top_level.txt
lib/metatutu/__init__.py
lib/metatutu/__version__.py
lib/metatutu/debugging.py
lib/metatutu/fsds.py
lib/metatutu/images.py
lib/metatutu/logging.py
lib/metatutu/osys.py
lib/metatutu/pipeline.py
lib/metatutu/app/__init__.py
lib/metatutu/app/cli.py
lib/metatutu/app/servicelet.py
lib/metatutu/apps3/__init__.py
lib/metatutu/apps3/caller.py
lib/metatutu/da/__init__.py
lib/metatutu/da/figure.py
lib/metatutu/dc/__init__.py
lib/metatutu/dc/capturing.py
lib/metatutu/dc/scanning.py
lib/metatutu/dc/scraping.py
lib/metatutu/jupyter/__init__.py
lib/metatutu/jupyter/display.py
lib/metatutu/messaging/__init__.py
lib/metatutu/messaging/smtp.py